bundling_score/__init__.py
bundling_score/bundling_score.py
bundling_score/main.py
bundling_score/plots.py
bundling_score/tools.py
bundling_score-0.1.4.dist-info/METADATA
bundling_score-0.1.4.dist-info/WHEEL
bundling_score-0.1.4.dist-info/entry_points.txt
bundling_score-0.1.4.dist-info/licenses/LICENSE
bundling_score-0.1.4.dist-info/RECORD
