Metadata-Version: 2.3
Name: bundling_score
Version: 0.1.4
Summary: Compute bundling score
Project-URL: Documentation, https://bundling_score.readthedocs.io/
Project-URL: Homepage, https://gitlab.college-de-france.fr/gdelabbey/bundling_score
Project-URL: Bug Tracker, https://gitlab.college-de-france.fr/gdelabbey/bundling_score/issues
Project-URL: Discussions, https://gitlab.college-de-france.fr/gdelabbey/bundling_score/discussions
Project-URL: Changelog, https://gitlab.college-de-france.fr/gdelabbey/bundling_score/releases
Author-email: Ghislain de Labbey <ghislain.de-labbey@college-de-france.fr>
License: 
License-File: LICENSE
Classifier: Development Status :: 1 - Planning
Classifier: Intended Audience :: Developers
Classifier: Intended Audience :: Science/Research
Classifier: Operating System :: MacOS
Classifier: Operating System :: POSIX :: Linux
Classifier: Programming Language :: Python
Classifier: Programming Language :: Python :: 3
Classifier: Programming Language :: Python :: 3 :: Only
Classifier: Programming Language :: Python :: 3.8
Classifier: Programming Language :: Python :: 3.9
Classifier: Programming Language :: Python :: 3.10
Classifier: Programming Language :: Python :: 3.11
Classifier: Topic :: Scientific/Engineering
Classifier: Typing :: Typed
Requires-Python: >=3.8
Requires-Dist: matplotlib
Requires-Dist: numpy
Requires-Dist: pandas
Requires-Dist: read-roi
Requires-Dist: scikit-image>=0.19.3
Requires-Dist: scikit-learn
Requires-Dist: scipy
Provides-Extra: dev
Requires-Dist: bundling-score[test]; extra == 'dev'
Requires-Dist: nox; extra == 'dev'
Provides-Extra: docs
Requires-Dist: myst-parser>=0.13; extra == 'docs'
Requires-Dist: sphinx-autoapi; extra == 'docs'
Requires-Dist: sphinx-book-theme>=0.1.0; extra == 'docs'
Requires-Dist: sphinx-copybutton; extra == 'docs'
Requires-Dist: sphinx>=4.0; extra == 'docs'
Provides-Extra: test
Requires-Dist: pytest-cov>=3; extra == 'test'
Requires-Dist: pytest>=6; extra == 'test'
